liquipediarl/__init__.py
liquipediarl/api.py
liquipediarl/constants.py
liquipediarl/player.py
liquipediarl-1.0.6.dist-info/METADATA
liquipediarl-1.0.6.dist-info/WHEEL
liquipediarl-1.0.6.dist-info/top_level.txt
liquipediarl-1.0.6.dist-info/RECORD
