Metadata-Version: 2.4
Name: liquipediarl
Version: 1.0.6
Summary: Liquipedia Rocket League API Wrapper
Home-page: https://github.com/8pq8/liquipediarl
Author: 8pq8
Classifier: Programming Language :: Python :: 3
Classifier: License :: OSI Approved :: MIT License
Requires-Python: >=3.7
Requires-Dist: requests
Requires-Dist: beautifulsoup4
Dynamic: author
Dynamic: classifier
Dynamic: description
Dynamic: description-content-type
Dynamic: home-page
Dynamic: requires-dist
Dynamic: requires-python
Dynamic: summary
